odoo10_addon_l10n_ch_zip-10.0.1.0.1-py2.7-nspkg.pth
odoo/addons/l10n_ch_zip/README.rst
odoo/addons/l10n_ch_zip/__init__.py
odoo/addons/l10n_ch_zip/__manifest__.py
odoo/addons/l10n_ch_zip/data/res.better.zip.csv
odoo/addons/l10n_ch_zip/i18n/de.po
odoo/addons/l10n_ch_zip/i18n/fr.po
odoo/addons/l10n_ch_zip/i18n/it.po
odoo/addons/l10n_ch_zip/i18n/nb_NO.po
odoo/addons/l10n_ch_zip/i18n/nl.po
odoo/addons/l10n_ch_zip/migrations/8.0.2.0.0/post-migration.py
odoo/addons/l10n_ch_zip/models/__init__.py
odoo/addons/l10n_ch_zip/models/better_zip.py
odoo/addons/l10n_ch_zip/static/description/icon.png
odoo10_addon_l10n_ch_zip-10.0.1.0.1.dist-info/DESCRIPTION.rst
odoo10_addon_l10n_ch_zip-10.0.1.0.1.dist-info/METADATA
odoo10_addon_l10n_ch_zip-10.0.1.0.1.dist-info/RECORD
odoo10_addon_l10n_ch_zip-10.0.1.0.1.dist-info/WHEEL
odoo10_addon_l10n_ch_zip-10.0.1.0.1.dist-info/metadata.json
odoo10_addon_l10n_ch_zip-10.0.1.0.1.dist-info/namespace_packages.txt
odoo10_addon_l10n_ch_zip-10.0.1.0.1.dist-info/top_level.txt
